meetspace/__init__.py
meetspace/exporters.py
meetspace/form_factory.py
meetspace/routes.py
meetspace/util.py
meetspace/validators.py
meetspace/schema/__init__.py
meetspace-0.0.1.dist-info/LICENSE
meetspace-0.0.1.dist-info/METADATA
meetspace-0.0.1.dist-info/WHEEL
meetspace-0.0.1.dist-info/top_level.txt
meetspace-0.0.1.dist-info/RECORD
