Metadata-Version: 2.1
Name: meetspace
Version: 0.0.1
Summary: web app for unifying meeting and event entry
Home-page: https://github.com/marcidy/meetspace
Author: Matt Arcidy
Author-email: marcidy@gmail.com
License: UNKNOWN
Keywords: meeting meetings event events
Platform: UNKNOWN
Classifier: Development Status :: 3 - Alpha
Classifier: Programming Language :: Python :: 3
